setup.cfg
setup.py
myriad/__init__.py
myriad/components.py
myriad/managers.py
myriad.egg-info/PKG-INFO
myriad.egg-info/SOURCES.txt
myriad.egg-info/dependency_links.txt
myriad.egg-info/entry_points.txt
myriad.egg-info/top_level.txt