Metadata-Version: 1.1
Name: myriad
Version: 0.1.2
Summary: Simple distributed computing.
Home-page: https://github.com/cjw85/myriad
Author: Chris Wright
Author-email: chris_wright1@outlook.com
License: UNKNOWN
Download-URL: https://github.com/cjw85/myriad/tarball/0.1.2
Platform: UNKNOWN
Classifier: Development Status :: 4 - Beta
Classifier: Intended Audience :: Developers
Classifier: License :: OSI Approved :: MIT License
Classifier: Natural Language :: English
Classifier: Programming Language :: Python
Classifier: Topic :: Software Development :: Libraries :: Python Modules
Classifier: Topic :: System :: Distributed Computing
